VideoToSMIServer/Server.py
VideoToSMIServer/__init__.py
VideoToSMI_Server-0.0.4.dist-info/LICENSE
VideoToSMI_Server-0.0.4.dist-info/METADATA
VideoToSMI_Server-0.0.4.dist-info/WHEEL
VideoToSMI_Server-0.0.4.dist-info/top_level.txt
VideoToSMI_Server-0.0.4.dist-info/RECORD
