Metadata-Version: 2.1
Name: VideoToSMI-Server
Version: 0.0.4
Summary: Create a smi file in Web based on the video
Home-page: https://github.com/Sotaneum/VideoToSMI-Server
Author: Donggun LEE
Author-email: gnyotnu39@gmail.com
License: UNKNOWN
Platform: UNKNOWN
Classifier: License :: OSI Approved :: MIT License
